  {
     "cig":"8872434428",
     "oggetto_bando":"DECRETI MINISTERO DELL'INTERNO DEL 30.01.2020 E DELL'11.11.2020 - INTERVENTI DI EFFICIENTAMENTO ENERGETICO - COMPLETAMENTO DELL'EFFICIENTAMENTO ENERGETICO DELL'ILLUMINAZIONE PUBBLICA.",
     "oggetto_lotto":"DECRETI MINISTERO DELL'INTERNO DEL 30.01.2020 E DELL'11.11.2020 - INTERVENTI DI EFFICIENTAMENTO ENERGETICO - COMPLETAMENTO DELL'EFFICIENTAMENTO ENERGETICO DELL'ILLUMINAZIONE PUBBLICA.",
     "oggetto_principale":"LAVORI",
     "cpv":"45231000-5",
     "desc_cpv":"LAVORI DI COSTRUZIONE DI CONDUTTURE LINEE DI COMUNICAZIONE E LINEE ELETTRICHE"
  }
