  {
     "cig":"88675841D0",
     "oggetto_bando":"AFFIDAMENTO DEL SERVIZIO RELATIVO ALL'AGGIORNAMENTO DEL QUADRO CONOSCITIVO E ALLA REDAZIONE DELLA VALSAT PER LE MATRICI SUOLO SOTTO SUOLO ACQUA RISCHIO IDRAULICO SISMICA SERVIZI ECOSISTEMICI E PAESAGGIO",
     "oggetto_lotto":"AFFIDAMENTO DEL SERVIZIO RELATIVO ALL'AGGIORNAMENTO DEL QUADRO CONOSCITIVO E ALLA REDAZIONE DELLA VALSAT PER LE MATRICI SUOLO SOTTO SUOLO ACQUA RISCHIO IDRAULICO SISMICA SERVIZI ECOSISTEMICI E PAESAGGIO",
     "oggetto_principale":"SERVIZI",
     "cpv":"71410000-5",
     "desc_cpv":"SERVIZI DI URBANISTICA"
  }
