  {
     "cig":"8867677E8B",
     "oggetto_bando":" SERVIZIO DI MEDIAZIONE ARTISTICA PER GLI ARTISTI CMQMARTINA E DURDUST RELATIVA ALL'ESIBIZIONE PREVISTA PER IL GIORNO 27 AGOSTO 2021 PRESSO FESTIVAL DELLE POLITICHE GIOVANILI RIPARTIRE FORO BOARIO.",
     "oggetto_lotto":" SERVIZIO DI MEDIAZIONE ARTISTICA PER GLI ARTISTI CMQMARTINA E DURDUST RELATIVA ALL'ESIBIZIONE PREVISTA PER IL GIORNO 27 AGOSTO 2021 PRESSO FESTIVAL DELLE POLITICHE GIOVANILI RIPARTIRE FORO BOARIO.",
     "oggetto_principale":"SERVIZI",
     "cpv":"92312240-5",
     "desc_cpv":"SERVIZI PRESTATI DA ARTISTI DELLO SPETTACOLO"
  }
