  {
     "cig":"8885458FE3",
     "oggetto_bando":"ACCORDI QUADRO PER L'ESECUZIONE DI LAVORI DI MANUTENZIONE NON PROGRAMMABILE ANCHE A CARATTERE D'URGENZA RELATIVI A PAVIMENTAZIONI LAPIDEE E/O TIPICHE - CORSIE E PISTE CICLABILI  ANCHE EVENTUALMENTE IN STRUTTURA -  INTERVENTI STRADALI VARI A SEGUITO DI SEGNALAZIONI ED OPERE ACCESSORIE IN AMBITO TERRITORIALE DI COMPETENZA DEI MUNICIPI DEL COMUNE DI GENOVA - MUNICIPI 1. CENTRO EST - 2. CENTRO OVEST (A) /    1. CENTRO EST - 2. CENTRO OVEST (B)/    1. CENTRO EST - 2. CENTRO OVEST (C)/    INTERO TERRITORIO (A) / INTERO TERRITORIO (B) - 5 LOTTI",
     "oggetto_lotto":"ACCORDO QUADRO PER L'ESECUZIONE DI LAVORI DI MANUTENZIONE NON PROGRAMMABILE ANCHE A CARATTERE D'URGENZA RELATIVI A PAVIMENTAZIONI LAPIDEE E/O TIPICHE - CORSIE E PISTE CICLABILI  ANCHE EVENTUALMENTE IN STRUTTURA -  INTERVENTI STRADALI VARI A SEGUITO DI SEGNALAZIONI ED OPERE ACCESSORIE IN AMBITO TERRITORIALE DI COMPETENZA DEI MUNICIPI DEL COMUNE DI GENOVA - LOTTO 4 INTERO TERRITORIO (A)  - LOTTO 4",
     "oggetto_principale":"LAVORI",
     "cpv":"45233140-2",
     "desc_cpv":"LAVORI STRADALI"
  }
