  {
     "cig":"88705208AB",
     "oggetto_bando":"LAVORI DI RIFACIMENTO DI N. 4 MANUFATTI IDRAULICI DEL COLATORE NERONE GARIGA NEI COMUNI DI CHIGNOLO PO E MIRADOLO TERME - FRAZ.NE CAMPORINALDO E DI UN MANUFATTO IDRAULICO DELLA ROGGIA DELLE CAMPANE NEL COMUNE DI SAN ZENONE AL PO",
     "oggetto_lotto":"LAVORI DI RIFACIMENTO DI N. 4 MANUFATTI IDRAULICI DEL COLATORE NERONE GARIGA NEI COMUNI DI CHIGNOLO PO E MIRADOLO TERME - FRAZ.NE CAMPORINALDO E DI UN MANUFATTO IDRAULICO DELLA ROGGIA DELLE CAMPANE NEL COMUNE DI SAN ZENONE AL PO",
     "oggetto_principale":"LAVORI",
     "cpv":"45240000-1",
     "desc_cpv":"LAVORI DI COSTRUZIONE PER OPERE IDRAULICHE"
  }
