  {
     "cig":"8857805BEA",
     "oggetto_bando":"PROGETTAZIONE ESECUTIVA ED ESECUZIONE DEI LAVORI DI REALIZZAZIONE DELLA NUOVA PALESTRA DELL'ISTITUTO COMPRENSIVO OLIVIERI SITA A PESARO IN VIA LAMARMORA",
     "oggetto_lotto":"PROGETTAZIONE ESECUTIVA ED ESECUZIONE DEI LAVORI DI REALIZZAZIONE DELLA NUOVA PALESTRA DELL'ISTITUTO COMPRENSIVO 'OLIVIERI' SITA A PESARO IN VIA LAMARMORA",
     "oggetto_principale":"LAVORI",
     "cpv":"45214200-2",
     "desc_cpv":"LAVORI DI COSTRUZIONE DI EDIFICI SCOLASTICI"
  }
