  {
     "cig":"8906261F11",
     "oggetto_bando":"DECRETO CRESCITA 2021 - EFFICIENTAMENTO ENERGETICO DELLA PUBBLICA ILLUMINAZIONE E INSTALLAZIONE DI TETTOIA FOTOVOLTAICA PER BIKE SHARING. - COLLAUDATORE IN CORSO D'OPERA.",
     "oggetto_lotto":"DECRETO CRESCITA 2021 - EFFICIENTAMENTO ENERGETICO DELLA PUBBLICA ILLUMINAZIONE E INSTALLAZIONE DI TETTOIA FOTOVOLTAICA PER BIKE SHARING. - COLLAUDATORE IN CORSO D'OPERA.",
     "oggetto_principale":"SERVIZI",
     "cpv":"71330000-0",
     "desc_cpv":"VARI SERVIZI DI INGEGNERIA"
  }
