  {
     "cig":"8854346577",
     "oggetto_bando":"RICHIESTA DI OFFERTA AI SENSI DELL'ART. 1 COMMA 2 LETTERA A) DEL DECRETO LEGGE 16 LUGLIO 2020 N. 76 PER L'AFFIDAMENTO DEL SERVIZIO TECNICO DI ARCHITETTURA E INGEGNERIA DI DIREZIONE LAVORI MISURA E CONTABILITÀ COORDINAMENTO DELLA SICUREZZA IN FASE DI ESECUZIONE DEI LAVORI DI OTTIMIZZAZIONE DELLE CONDIZIONI DI SICUREZZA VEICOLARE E PEDONALE SULLO SNODO DI PIAZZA CAVOUR",
     "oggetto_lotto":"RICHIESTA DI OFFERTA AI SENSI DELL'ART. 1 COMMA 2 LETTERA A) DEL DECRETO LEGGE 16 LUGLIO 2020 N. 76 PER L'AFFIDAMENTO DEL SERVIZIO TECNICO DI ARCHITETTURA E INGEGNERIA DI DIREZIONE LAVORI MISURA E CONTABILITÀ COORDINAMENTO DELLA SICUREZZA IN FASE DI ESECUZIONE DEI LAVORI DI OTTIMIZZAZIONE DELLE CONDIZIONI DI SICUREZZA VEICOLARE E PEDONALE SULLO SNODO DI PIAZZA CAVOUR",
     "oggetto_principale":"SERVIZI",
     "cpv":"71240000-2",
     "desc_cpv":"SERVIZI ARCHITETTONICI DI INGEGNERIA E PIANIFICAZIONE"
  }
