  {
     "cig":"8856159D97",
     "oggetto_bando":"NEXUS 360 JUBILEE 240 JUBILEE 240 - ADESIVO PANNELLO DI CHIUSURA PER JUBILEE 240 KIT CONNESSIONE SPESE DI IMBALLO E TRASPORTO KIT CONNESSIONE JUBILEE 240  NEXUS ",
     "oggetto_lotto":"NEXUS 360 JUBILEE 240 JUBILEE 240 - ADESIVO PANNELLO DI CHIUSURA PER JUBILEE 240 KIT CONNESSIONE SPESE DI IMBALLO E TRASPORTO KIT CONNESSIONE JUBILEE 240  NEXUS ",
     "oggetto_principale":"FORNITURE",
     "cpv":"44613700-7",
     "desc_cpv":"CASSONETTI PER RIFIUTI"
  }
