  {
     "cig":"8805305F8A",
     "oggetto_bando":"SERVIZI DI ARCHITETTURA E INGEGNERIA RELATIVO ALLA PROGETTAZIONE DEFINITIVA DEI  LAVORI DI RISTRUTTURAZIONE DELL'EDIFICIO EX EAS DI VIA IMPALLOMENI IN USO AL MINISTERO DELLA GIUSTIZIA ",
     "oggetto_lotto":"SERVIZI DI ARCHITETTURA E INGEGNERIA RELATIVO ALLA PROGETTAZIONE DEFINITIVA DEI  LAVORI DI RISTRUTTURAZIONE DELL'EDIFICIO EX EAS DI VIA IMPALLOMENI IN USO AL MINISTERO DELLA GIUSTIZIA",
     "oggetto_principale":"SERVIZI",
     "cpv":"71330000-0",
     "desc_cpv":"VARI SERVIZI DI INGEGNERIA"
  }
