{"celex_id": "31984R1047", "uri": "http://publications.europa.eu/resource/cellar/98ac2d97-2b66-4374-a279-7efa2c12daf4", "type": "Regulation", "concepts": ["1233", "1277", "1570", "2958", "3568", "386"], "title": "Commission Regulation (EEC) No 1047/84 of 13 April 1984 amending the Annex to Regulation (EEC) No 532/75 concerning the recovery on exportation of aids granted in respect of skimmed-milk powder for use as feed and in respect of skimmed milk processed into compound feedingstuffs\n", "header": "COMMISSION  REGULATION (EEC) No 1047/84\nof 13 April 1984\namending the Annex to Regulation (EEC) No 532/75 concerning the recovery on exportation of aids granted in respect of skimmed-milk powder for use as feed and in respect of skimmed milk processed into compound feedingstuffs\nTHE COMMISSION OF THE EUROPEAN\nCOMMUNITIES", "recitals": ",\nHaving regard to the Treaty establishing the European Economic Community,\nHaving regard to Council Regulation (EEC) No 804/68 of 27 June 1968 on the common organization of the market in milk and milk products (1), as last amended by Regulation (EEC) No 856/84 (2), and in particular Article 10 (3) thereof,\nWhereas the second subparagraph of Article 2 (1) of Council Regulation (EEC) No 986/68 (3), as last amended by Regulation (EEC) No 867/84 (4), provides that where skimmed milk or skimmed-milk powder is exported in the form of denatured skimmed-milk powder or compound feedingstuffs any aid paid out in respect thereof is to be recovered; whereas, to that end, an amount equal to the amount of the aid is to be charged at the time of exportation; whereas the amounts to be so charged and the administrative procedure to be followed in such case were fixed by Commission Regulation (EEC) No 532/75 (5), as last amended by Regulation (EEC) No 3215/83 (6);\nWhereas the amounts to be recovered should be brought into line with the aid for the skimmed-milk powder payable with effect from 9 April 1984; whereas it is, however, necessary to ensure that the new amounts chargeable are not levied on products in respect of which no aid or aid at the previous lower rate was paid;\nWhereas the measures provided for in this Regulation are in accordance with the opinion of the Management Committee for Milk and Milk Products,", "main_body": ["1. With effect from 16 April 1984 the Annex to Regulation (EEC) No 532/75 is replaced by the Annex to this Regulation.\n2. However in the case of skimmed-milk powder in respect of which proof is furnished that only the aid at the rate operative before 9 April 1984 has been paid, the amounts to be collected shall be the amounts chargeable before that date.", "This Regulation shall enter into force on the third day following its publication in the Official Journal of the European Communities.\nIt shall apply with effect from 16 April 1984.\nThis Regulation shall be binding in its entirety and directly applicable in all Member States."], "attachments": "Done at Brussels, 13 April 1984.\nFor the Commission\nPoul DALSAGER\nMember of the Commission\n(1) OJ No L 148, 28. 6. 1968, p. 13.\n(2) OJ No L 90, 1. 4. 1984, p. 10.\n(3) OJ No L 169, 18. 7. 1968, p. 4.\n(4) OJ No L 90, 1. 4. 1984, p. 29.\n(5) OJ No L 56, 3. 3. 1975, p. 20.\n(6) OJ No L 318, 16. 11. 1983, p. 10.\nANNEX\n1.2.3.4 //   //   //  1.2.3,4 // CCT heading No  // Description  // Amount to be charged (ECU/100 kg)  //   //  //   //   //   //   // 23.07  // Sweetened forage; other preparations of a kind used in animal feeding:  //   //   // B. Other, containing starch, glucose, glucose syrup, maltodextrine or maltodextrine syrup, falling within subheadings 17.02 B and 21.07 F II, or milk products:  //   //   // I. Containing starch, glucose, glucose syrup, maltodextrine or maltodextrine syrup:  //   //   // a) Containing no starch or containing 10 % or less by weight of starch:  //   //   // ex 1. Containing less than 10 % by weight of milk products:  //   //   // aa) Containing no milk powder (*)  // -  //   // bb) Containing less than 10 % by weight of milk powder (*)  // 6,57  //  // 2. Containing 10 % or more but less than 50 % by weight of milk products:  //   //   // aa) Containing no milk powder (*)  // -  //   // bb) Containing:  //   //   // (11) less than 30 %  // 21,17  //   // (22) not less than 30 % by weight of milk powder (*)  // 35,77  //   // 3. Containing 50 % or more but less than 75 % by weight of milk products:  //   //   // aa) Containing no milk powder (*)  // -  //   // bb) Containing:  //   //   // (11) less than 30 %  // 21,17  //   // (22) not less than 30 % but less than 40 %  // 25,55  //   // (33) not less than 40 % but less than 50 %  // 32,85  //   // (44) not less than 50 % but less than 60 %  // 40,15  //   // (55) not less than 60 % but less than 70 %  // 47,45  //   // (66) not less than 70 % by weight of milk powder (*)  // 52,93  //  // 4. Containing 75 % or more by weight of milk products:  //  //   // aa) Containing no milk powder (*)  // -  //   // bb) Containing:  //   //   // (11) less than 30 %  // 21,17  //  // (22) not less than 30 % but less than 40 %  // 25,55  //  // (33) not less than 40 % but less than 50 %  // 32,85  //  // (44) not less than 50 % but less than 60 %  // 40,15  //  // (55) not less than 60 % but less than 70 %  // 47,45  //  // (66) not less than 70 % but less than 75 %  // 52,93  //  // (77) not less than 75 % but less than 80 %  // 57,31  //  // (88) not less than 80 % by weight of milk powder (*)  // 62,05 1.2.3.4 //   //   //  1.2.3,4 // CCT heading No  // Description  // Amount to be charged (ECU/100 kg)  //   //   //   //  // 23.07 (cont'd)  // B. I. b) Containing more than 10 % but not more than 30 % by weight of starch:  //   //   // ex 1. Containing less than 10 % by weight of milk products:  //   //  // aa) Containing no milk powder (*)  // -  //   // bb) Containing less than 10 % by weight of milk powder (*)  // 6,57  //   // 2. Containing 10 % or more but less than 50 % by weight of milk products:  //   //   // aa) Containing no milk powder (*)  // -  //   // bb) Containing:  //   //   // (11) less than 30 %  // 21,17  //   // (22) not less than 30 % by weight of milk powder (*)  // 35,77  //   // 3. Containing 50 % or more by weight of milk products:  //   //   // aa) Containing no milk powder (*)  // -  //   // bb) Containing:  //   //   // (11) less than 60 %  // 40,15  //   // (22) not less than 60 % by weight of milk powder (*)  // 58,40  //  // c) Containing more than 30 % by weight of starch:  //   //  // ex 1. Containing less than 10 % by weight of milk products:  //   //   // aa) Containing no milk powder (*)  // -  //  // bb) Containing less than 10 % by weight of milk powder (*)  // 6,57  //   // 2. Containing 10 % or more but less than 50 % by weight of milk products:  //   //   // aa) Containing no milk powder (*)  // -  //   // bb) Containing:  //   //  // (11) less than 30 %  // 21,17  //   // (22) not less than 30 % by weight of milk powder (*)  // 35,77  //   // 3. Containing 50 % or more by weight of milk products:  //   //  // aa) Containing no milk powder (*)  // -  //   // bb) Containing:  //   //   // (11) less than 60 %  // 40,15  //  // (22) not less than 60 % by weight of milk powder (*)  // 47,45  //   // II. Containing no starch, glucose, glucose syrup, maltodextrine or maltodextrine syrup, but containing milk products:  //   //   // a) Containing no milk powder (*)  // -  //   // b) Other  // 62,05  //   //   //\n(*) For the purposes of this Regulation, 'milk powder' means a product falling within subheading 04.02 A II b) 1 or 2, having a fat content, by weight, not exceeding 11 %."}