{"celex_id": "32006R0152", "uri": "http://publications.europa.eu/resource/cellar/b6c90641-6f10-48c3-a157-7c10c1229185", "type": "Regulation", "concepts": ["1118", "1605", "2635", "5231", "693"], "title": "Commission Regulation (EC) No\u00a0152/2006 of  27 January 2006  establishing the standard import values for determining the entry price of certain fruit and vegetables\n", "header": "28.1.2006 EN Official Journal of the European Union L 25/8\nCOMMISSION REGULATION (EC) No 152/2006\nof 27 January 2006\nestablishing the standard import values for determining the entry price of certain fruit and vegetables\nTHE COMMISSION OF THE EUROPEAN COMMUNITIES", "recitals": ",\nHaving regard to the Treaty establishing the European Community,\nHaving regard to Commission Regulation (EC) No 3223/94 of 21 December 1994 on detailed rules for the application of the import arrangements for fruit and vegetables\u00a0(1), and in particular Article 4(1) thereof,\nWhereas:\n(1) Regulation (EC) No 3223/94 lays down, pursuant to the outcome of the Uruguay Round multilateral trade negotiations, the criteria whereby the Commission fixes the standard values for imports from third countries, in respect of the products and periods stipulated in the Annex thereto.\n(2) In compliance with the above criteria, the standard import values must be fixed at the levels set out in the Annex to this Regulation,", "main_body": ["The standard import values referred to in Article 4 of Regulation (EC) No 3223/94 shall be fixed as indicated in the Annex hereto.", "This Regulation shall enter into force on 28 January 2006.\nThis Regulation shall be binding in its entirety and directly applicable in all Member States."], "attachments": "Done at Brussels, 27 January 2006.\nFor the Commission\nJ. L. DEMARTY\nDirector-General for Agriculture and Rural Development\n(1)\u00a0\u00a0OJ L 337, 24.12.1994, p. 66. Regulation as last amended by Regulation (EC) No 386/2005 (OJ L 62, 9.3.2005, p. 3).\nANNEX\nto Commission Regulation of 27 January 2006 establishing the standard import values for determining the entry price of certain fruit and vegetables\n(EUR/100 kg)\nCN code Third country code\u00a0(1) Standard import value\n0702\u00a000\u00a000 052 112,9\n204 43,4\n212 97,4\n624 120,2\n999 93,5\n0707\u00a000\u00a005 052 151,5\n204 102,3\n628 155,5\n999 136,4\n0709\u00a010\u00a000 220 80,1\n624 91,7\n999 85,9\n0709\u00a090\u00a070 052 146,3\n204 148,6\n999 147,5\n0805\u00a010\u00a020 052 44,2\n204 54,8\n212 52,8\n220 50,9\n624 58,3\n999 52,2\n0805\u00a020\u00a010 204 79,3\n999 79,3\n0805\u00a020\u00a030, 0805\u00a020\u00a050, 0805\u00a020\u00a070, 0805\u00a020\u00a090 052 61,1\n204 100,0\n400 86,0\n464 148,0\n624 78,3\n662 32,0\n999 84,2\n0805\u00a050\u00a010 052 57,8\n220 61,7\n999 59,8\n0808\u00a010\u00a080 400 130,4\n404 107,0\n720 68,7\n999 102,0\n0808\u00a020\u00a050 388 113,3\n400 83,1\n720 48,3\n999 81,6\n(1)\u00a0\u00a0Country nomenclature as fixed by Commission Regulation (EC) No 750/2005 (OJ L 126, 19.5.2005, p. 12). Code \u2018999\u2019 stands for \u2018of other origin\u2019."}